normattiva2md/__init__.py
normattiva2md/akoma_utils.py
normattiva2md/api.py
normattiva2md/cli.py
normattiva2md/constants.py
normattiva2md/exa_api.py
normattiva2md/exceptions.py
normattiva2md/markdown_converter.py
normattiva2md/models.py
normattiva2md/multi_document.py
normattiva2md/normattiva_api.py
normattiva2md/provvedimenti_api.py
normattiva2md/py.typed
normattiva2md/utils.py
normattiva2md/validation.py
normattiva2md/xml_parser.py
normattiva2md/schemas/validation_report_schema.json
normattiva2md-2.1.10.dist-info/licenses/LICENSE
normattiva2md-2.1.10.dist-info/METADATA
normattiva2md-2.1.10.dist-info/WHEEL
normattiva2md-2.1.10.dist-info/entry_points.txt
normattiva2md-2.1.10.dist-info/top_level.txt
normattiva2md-2.1.10.dist-info/RECORD
