Metadata-Version: 2.4
Name: normattiva2md
Version: 2.1.10
Summary: Convertitore da XML Akoma Ntoso a formato Markdown con download automatico delle leggi citate e cross-references inline (CLI: normattiva2md)
Home-page: https://github.com/ondata/normattiva_2_md
Author: Andrea Borruso
Author-email: Andrea Borruso <aborruso@gmail.com>
License: MIT
Project-URL: Homepage, https://github.com/ondata/normattiva_2_md
Project-URL: Repository, https://github.com/ondata/normattiva_2_md
Project-URL: Issues, https://github.com/ondata/normattiva_2_md/issues
Keywords: akoma,ntoso,xml,markdown,converter,legal,documents,normattiva
Classifier: Development Status :: 5 - Production/Stable
Classifier: Intended Audience :: Developers
Classifier: Intended Audience :: Legal Industry
Classifier: License :: OSI Approved :: MIT License
Classifier: Operating System :: OS Independent
Classifier: Programming Language :: Python :: 3
Classifier: Programming Language :: Python :: 3.7
Classifier: Programming Language :: Python :: 3.8
Classifier: Programming Language :: Python :: 3.9
Classifier: Programming Language :: Python :: 3.10
Classifier: Programming Language :: Python :: 3.11
Classifier: Programming Language :: Python :: 3.12
Classifier: Topic :: Text Processing :: Markup
Classifier: Topic :: Text Processing :: Markup :: XML
Classifier: Topic :: Software Development :: Libraries :: Python Modules
Requires-Python: >=3.7
License-File: LICENSE
Requires-Dist: requests>=2.25.0
Requires-Dist: rich<14.0.0,>=13.0.0
Dynamic: author
Dynamic: home-page
Dynamic: license-file
Dynamic: requires-python
